sysv_ipc.cpython-310-darwin.so
sysv_ipc-1.2.0.dist-info/RECORD
sysv_ipc-1.2.0.dist-info/WHEEL
sysv_ipc-1.2.0.dist-info/top_level.txt
sysv_ipc-1.2.0.dist-info/METADATA
sysv_ipc-1.2.0.dist-info/licenses/LICENSE
