Metadata-Version: 2.1
Name: sysv_ipc
Version: 1.2.0
Summary: SysV IPC primitives (semaphores, shared memory and message queues) for Python
Author-email: Philip Semanchuk <philip@semanchuk.com>
License: BSD-3-Clause
Project-URL: Homepage, https://github.com/osvenskan/sysv_ipc/
Classifier: Development Status :: 5 - Production/Stable
Classifier: Intended Audience :: Developers
Classifier: Operating System :: MacOS :: MacOS X
Classifier: Operating System :: POSIX :: BSD :: FreeBSD
Classifier: Operating System :: POSIX :: Linux
Classifier: Operating System :: POSIX :: SunOS/Solaris
Classifier: Operating System :: POSIX
Classifier: Operating System :: Unix
Classifier: Programming Language :: Python
Classifier: Programming Language :: Python :: 3
Classifier: Topic :: Utilities
License-File: LICENSE
